<?xml version="1.0" encoding="UTF-8"?>
<ProjectsViewInfo>
	<DiagramOpenInfos activeDiagramId="G0yz9RqD.AACAQOr">
		<Info bounds="Re:0.0,0.0,1299.0,603.0" diagramId="G0yz9RqD.AACAQOr" maximized="true" offsetX="0" offsetY="0"/>
	</DiagramOpenInfos>
	<DiagramLastActivated>
		<Diagram id="G0yz9RqD.AACAQOr" time="1483567459593"/>
		<Diagram id="Use Case Statement" time="0"/>
		<Diagram id="UeXceler Use Case" time="0"/>
		<Diagram id="User Story" time="0"/>
		<Diagram id="Sprint" time="0"/>
	</DiagramLastActivated>
</ProjectsViewInfo>